aws_cdk_construct_devops01ua/__init__.py
aws_cdk_construct_devops01ua/constructs.py
aws_cdk_construct_devops01ua-0.0.6.dist-info/METADATA
aws_cdk_construct_devops01ua-0.0.6.dist-info/WHEEL
aws_cdk_construct_devops01ua-0.0.6.dist-info/top_level.txt
aws_cdk_construct_devops01ua-0.0.6.dist-info/RECORD
