Metadata-Version: 2.1
Name: aws_cdk_construct_devops01ua
Version: 0.0.6
Summary: Sample of custom AWS CDK construct for demo purposes
Author: Artem Hrechanychenko
Author-email: devops01ua@gmail.com
Classifier: License :: OSI Approved :: MIT License
Classifier: Programming Language :: Python :: 3
Classifier: Programming Language :: Python :: 3.6
Classifier: Programming Language :: Python :: 3.7
Classifier: Programming Language :: Python :: 3.8
Classifier: Programming Language :: Python :: 3.9
Classifier: Programming Language :: Python :: 3.10
Requires-Python: >=3.6
Requires-Dist: aws-cdk-lib >=2.0.0
Requires-Dist: constructs >=10.0.0
